taugeometric/__init__.py
taugeometric/astar/__funcs__.py
taugeometric/astar/__init__.py
taugeometric/poresSE/__funcs__.py
taugeometric/poresSE/__init__.py
taugeometric/tortuosity/__funcs__.py
taugeometric/tortuosity/__init__.py
taugeometric-1.0.2.dist-info/LICENSE
taugeometric-1.0.2.dist-info/METADATA
taugeometric-1.0.2.dist-info/WHEEL
taugeometric-1.0.2.dist-info/top_level.txt
taugeometric-1.0.2.dist-info/RECORD
